vert_tree/__init__.py
vert_tree/base.py
vert_tree/common.py
vert_tree/curses_display.py
vert_tree/terminal_display.py
vert_tree-1.1.dist-info/LICENSE
vert_tree-1.1.dist-info/METADATA
vert_tree-1.1.dist-info/WHEEL
vert_tree-1.1.dist-info/top_level.txt
vert_tree-1.1.dist-info/RECORD
