Metadata-Version: 2.1
Name: vert-tree
Version: 1.1
Summary: Small library to visually display binary trees in terminal or curses pad.
Home-page: https://github.com/kepplemr/vert_tree
Author: Michael Kepple
Author-email: kepplemr@gmail.com
License: UNKNOWN
Project-URL: Bug Tracker, https://github.com/kepplemr/vert_tree/issues
Platform: UNKNOWN
Classifier: Programming Language :: Python :: 2.7
Classifier: Programming Language :: Python :: 3.5
Classifier: Programming Language :: Python :: 3.6
Classifier: Programming Language :: Python :: 3.7
Classifier: Programming Language :: Python :: 3.8
Classifier: Programming Language :: Python :: 3.9
Classifier: License :: OSI Approved :: GNU General Public License v3 (GPLv3)
Classifier: Operating System :: OS Independent
Requires-Python: >=2.7
License-File: LICENSE
